LICENSE
MANIFEST.in
README.md
pyproject.toml
requirements.txt
requirements_dev.txt
setup.cfg
setup.py
bg_space/__init__.py
bg_space/core.py
bg_space/functions.py
bg_space/utils.py
bg_space.egg-info/PKG-INFO
bg_space.egg-info/SOURCES.txt
bg_space.egg-info/dependency_links.txt
bg_space.egg-info/not-zip-safe
bg_space.egg-info/requires.txt
bg_space.egg-info/top_level.txt