Metadata-Version: 2.1
Name: bg-space
Version: 0.6.0
Summary: Anatomical space conventions made easy
Home-page: https://github.com/brainglobe/bg-space
Author: Luigi Petrucco @portugueslab
Author-email: luigi.petrucco@gmail.com
Classifier: Development Status :: 3 - Alpha
Classifier: Operating System :: POSIX :: Linux
Classifier: Operating System :: Microsoft :: Windows :: Windows 10
Classifier: Operating System :: MacOS :: MacOS X
Classifier: Programming Language :: Python
Classifier: Programming Language :: Python :: 3.6
Classifier: Programming Language :: Python :: 3.7
Classifier: Programming Language :: Python :: 3.8
Classifier: Intended Audience :: Science/Research
Requires-Python: >=3.6
Provides-Extra: dev
License-File: LICENSE
